comfyui_nitra/nitra_server.pyd
comfyui_nitra/__init__.py
comfyui_nitra/web/model_downloads.pyd
comfyui_nitra/web/package_installer.pyd
comfyui_nitra/web/workflow_downloader.pyd
comfyui_nitra/web/__init__.py
comfyui_nitra/web/installers/cuda_installer.pyd
comfyui_nitra/web/installers/onnxruntime_installer.pyd
comfyui_nitra/web/installers/pytorch_installer.pyd
comfyui_nitra/web/installers/sageattention_installer.pyd
comfyui_nitra/web/installers/shared.pyd
comfyui_nitra/web/installers/triton_installer.pyd
comfyui_nitra/web/installers/vs_build_tools_installer.pyd
comfyui_nitra/web/installers/__init__.py
comfyui_nitra/web/setup_modules/auth.pyd
comfyui_nitra/web/setup_modules/config.pyd
comfyui_nitra/web/setup_modules/custom_nodes.pyd
comfyui_nitra/web/setup_modules/downloads.pyd
comfyui_nitra/web/setup_modules/environment.pyd
comfyui_nitra/web/setup_modules/file_operations.pyd
comfyui_nitra/web/setup_modules/logging_setup.pyd
comfyui_nitra/web/setup_modules/utils.pyd
comfyui_nitra/web/setup_modules/__init__.py
comfyui_nitra-1.0.54.dist-info/METADATA
comfyui_nitra-1.0.54.dist-info/top_level.txt
comfyui_nitra-1.0.54.dist-info/WHEEL
comfyui_nitra-1.0.54.dist-info/RECORD
