Metadata-Version: 2.4
Name: comfyui-nitra
Version: 1.0.54
Summary: Nitra custom node for ComfyUI
Author: Nitra Labs
License: Proprietary
Project-URL: Homepage, https://github.com/TheArtOfficial/ComfyUI-Nitra
Classifier: Development Status :: 4 - Beta
Classifier: Intended Audience :: Developers
Classifier: Operating System :: OS Independent
Classifier: Programming Language :: Python :: 3
Classifier: Programming Language :: Python :: 3.9
Classifier: Programming Language :: Python :: 3.10
Classifier: Programming Language :: Python :: 3.11
Classifier: Programming Language :: Python :: 3.12
Requires-Python: >=3.9
Requires-Dist: requests>=2.31.0
Requires-Dist: huggingface_hub[hf_transfer]
Requires-Dist: hf_xet
Requires-Dist: keyring>=24.3.0
Dynamic: requires-python
